README.rst
flask_xstatic_files.py
setup.cfg
setup.py
Flask_XStatic_Files.egg-info/PKG-INFO
Flask_XStatic_Files.egg-info/SOURCES.txt
Flask_XStatic_Files.egg-info/dependency_links.txt
Flask_XStatic_Files.egg-info/not-zip-safe
Flask_XStatic_Files.egg-info/requires.txt
Flask_XStatic_Files.egg-info/top_level.txt