Metadata-Version: 1.1
Name: Flask-XStatic-Files
Version: 0.0.2
Summary: Easily use XStatic files in flask
Home-page: http://github.com/agx/flask-xstatic-files
Author: Guio Günther
Author-email: agx@sigxcpu.org
License: LGPLv3+
Platform: any
Classifier: Environment :: Web Environment
Classifier: Intended Audience :: Developers
Classifier: License :: OSI Approved :: GNU Lesser General Public License v3 or later (LGPLv3+)
Classifier: Operating System :: OS Independent
Classifier: Programming Language :: Python
Classifier: Topic :: Internet :: WWW/HTTP :: Dynamic Content
Classifier: Topic :: Software Development :: Libraries :: Python Modules
